yourdfpy/__init__.py
yourdfpy/urdf.py
yourdfpy/viz.py
yourdfpy-0.0.58.dist-info/licenses/AUTHORS.md
yourdfpy-0.0.58.dist-info/licenses/LICENSE.txt
yourdfpy-0.0.58.dist-info/METADATA
yourdfpy-0.0.58.dist-info/WHEEL
yourdfpy-0.0.58.dist-info/entry_points.txt
yourdfpy-0.0.58.dist-info/top_level.txt
yourdfpy-0.0.58.dist-info/RECORD
