Metadata-Version: 2.4
Name: yourdfpy
Version: 0.0.58
Summary: A simpler and easier-to-use library for loading, manipulating, saving, and visualizing URDF files.
Home-page: https://github.com/clemense/yourdfpy/
Author: Clemens Eppner
Author-email: clemens.eppner@gmail.com
License: MIT
Project-URL: Source, https://github.com/clemense/yourdfpy/
Platform: any
Classifier: Development Status :: 4 - Beta
Classifier: Programming Language :: Python
Classifier: Programming Language :: Python :: 3
Classifier: Programming Language :: Python :: 3.7
Classifier: Programming Language :: Python :: 3.8
Classifier: Intended Audience :: Developers
Classifier: License :: OSI Approved :: MIT License
Classifier: Operating System :: POSIX :: Linux
Classifier: Operating System :: Unix
Classifier: Operating System :: MacOS
Classifier: Operating System :: Microsoft :: Windows
Requires-Python: >=3.7
License-File: LICENSE.txt
License-File: AUTHORS.md
Requires-Dist: importlib-metadata; python_version < "3.8"
Requires-Dist: lxml
Requires-Dist: trimesh[easy]>=3.11.2
Requires-Dist: numpy
Requires-Dist: six
Provides-Extra: full
Requires-Dist: pyglet<2; extra == "full"
Provides-Extra: testing
Requires-Dist: setuptools; extra == "testing"
Requires-Dist: pytest; extra == "testing"
Requires-Dist: pytest-cov; extra == "testing"
Dynamic: license-file
